setup.py
custom_flet/__init__.py
custom_flet.egg-info/PKG-INFO
custom_flet.egg-info/SOURCES.txt
custom_flet.egg-info/dependency_links.txt
custom_flet.egg-info/top_level.txt
custom_flet/components/__init__.py
custom_flet/components/custom_icon.py
custom_flet/components/custom_icon_button.py
custom_flet/components/elevated_custom_logo_button.py