Metadata-Version: 2.1
Name: custom-flet
Version: 0.1.3
Summary: package containing custom flet controls for ease of use.
Author: Subhradeep Rang
Author-email: srang992@gmail.com
